rolesnap/__init__.py
rolesnap/cli.py
rolesnap/constants.py
rolesnap/logging.py
rolesnap/py.typed
rolesnap/core/__init__.py
rolesnap/core/engine.py
rolesnap/core/models.py
rolesnap/core/paths.py
rolesnap/core/planner.py
rolesnap/core/selfscan.py
rolesnap/core/yaml_loader.py
rolesnap/examples/rolesnap_example.yaml
rolesnap-0.9.2.dist-info/licenses/LICENSE
rolesnap-0.9.2.dist-info/METADATA
rolesnap-0.9.2.dist-info/WHEEL
rolesnap-0.9.2.dist-info/entry_points.txt
rolesnap-0.9.2.dist-info/top_level.txt
rolesnap-0.9.2.dist-info/RECORD
