Metadata-Version: 2.4
Name: rolesnap
Version: 0.9.2
Summary: Structured, role-based code snapshots for LLMs. Enforce architecture boundaries.
Author-email: Sense1Tapo4ek <egorssupermail@gmail.com>
License: MIT License
Project-URL: Homepage, https://github.com/MeshcheryTapo4ek/snapshot-pepester
Project-URL: Changelog, https://meshcherytapo4ek.github.io/snapshot-pepester/changelog/
Project-URL: Issues, https://github.com/MeshcheryTapo4ek/snapshot-pepester/issues
Project-URL: Documentation, https://meshcherytapo4ek.github.io/snapshot-pepester
Keywords: architecture,snapshot,LLM,hexagonal,modules,context,monorepo
Classifier: Programming Language :: Python :: 3
Classifier: Programming Language :: Python :: 3.11
Classifier: Programming Language :: Python :: 3.12
Classifier: Programming Language :: Python :: 3.13
Classifier: Environment :: Console
Classifier: Intended Audience :: Developers
Classifier: License :: OSI Approved :: MIT License
Classifier: Topic :: Software Development :: Build Tools
Classifier: Typing :: Typed
Requires-Python: >=3.11
License-File: LICENSE
Requires-Dist: pyyaml>=6.0.2
Requires-Dist: python-dotenv>=1.0.1
Requires-Dist: rich>=13.7.1
Provides-Extra: dev
Requires-Dist: pytest; extra == "dev"
Requires-Dist: mypy; extra == "dev"
Requires-Dist: ruff; extra == "dev"
Requires-Dist: pre-commit; extra == "dev"
Requires-Dist: types-PyYAML; extra == "dev"
Requires-Dist: hypothesis; extra == "dev"
Dynamic: license-file
